{
  "검증_요약": {
    "총_문제수": 12,
    "검증_일시": "2025-07-03T21:55:50.496583",
    "검증_방식": "5점_척도_품질평가",
    "품질_평가_평균": {
      "적절성": 4.33,
      "난이도 적정성": 3.83,
      "명확성 및 모호성 없음": 4.67,
      "정답 및 해설의 정확성": 4.83,
      "학습적 가치 및 유용성": 4.08
    },
    "Quality_Score_평균": 21.75,
    "Quality_Score_최대": 25,
    "품질등급": "Good",
    "충실도_검증_평균": {
      "문서_충실도": 1.83
    },
    "충실도_전체_평균": 1.83,
    "충실도_최대점수": 2
  },
  "검증_기준": {
    "품질_평가_기준": {
      "적절성": "문제가 학습 목표와 수준에 적합한지 - 5점: 매우 적절, 3점: 보통, 1점: 부적절",
      "난이도 적정성": "문제 난이도가 명시된 레벨에 적합한지 - 5점: 매우 적절, 3점: 보통, 1점: 부적절",
      "명확성 및 모호성 없음": "문제와 선택지가 명확하고 모호하지 않은지 - 5점: 매우 명확, 3점: 보통, 1점: 모호함",
      "정답 및 해설의 정확성": "정답과 해설이 정확하고 논리적인지 - 5점: 완전 정확, 3점: 대체로 정확, 1점: 오류 있음",
      "학습적 가치 및 유용성": "교육적 효과와 실무 활용도가 높은지 - 5점: 매우 유용, 3점: 보통, 1점: 낮음"
    },
    "충실도_검증_기준": {
      "문서_충실도": "원본 문서와의 일치성 - 2점: 완전한 근거(직접 서술), 1점: 부분적 근거(추론 필요), 0점: 근거 없음(무관/모순)"
    }
  },
  "문제별_검증결과": [
    {
      "question_id": 1,
      "question_info": {
        "type": "OBJECTIVE",
        "difficulty_level": "NORMAL",
        "tags": [
          "이해력"
        ],
        "source_file": "basic_questions_20250703_215032.json",
        "document_name": "doc_2_ags_trouble_shooting_v1_1",
        "question": "SK C&C의 AGS 인력이 ServiceFLOW를 통해 IT 지원을 요청할 때, 가장 먼저 수행해야 하는 작업은 무엇입니까?"
      },
      "quality_evaluation": {
        "적절성": {
          "점수": 4,
          "평가사유": "문제가 SK C&C의 AGS 인력이 ServiceFLOW를 통해 IT 지원을 요청하는 상황에 적합하며, 수준은 적당함."
        },
        "난이도 적정성": {
          "점수": 4,
          "평가사유": "문제의 난이도가 중간(MEDIUM) 수준에 적합하며, 적정한 난이도를 제공함."
        },
        "명확성 및 모호성 없음": {
          "점수": 5,
          "평가사유": "문제와 선택지가 명확하게 제시되어 있고, 모호성이 전혀 없음."
        },
        "정답 및 해설의 정확성": {
          "점수": 5,
          "평가사유": "정답 '문의 접수' 선택이 정확하게 제시되었고, 해설 역시 정확하고 논리적으로 설명되어 있음."
        },
        "학습적 가치 및 유용성": {
          "점수": 4,
          "평가사유": "이 문제를 풀면 SK C&C의 AGS 인력이 IT 지원을 요청할 때의 절차를 학습할 수 있으며, 실무에서도 유용하게 활용 가능함."
        },
        "Quality Score": 22,
        "Quality Score 최대": 25,
        "품질등급": "Excellent",
        "종합평가": "문제는 적절하고 적정한 난이도를 가지며 명확하고 정확한 내용을 담고 있습니다. 다소 높은 학습적 가치와 유용성을 제공하며, 개선할 부분은 거의 없습니다."
      },
      "fidelity_evaluation": {
        "문서_충실도": {
          "점수": 2,
          "검증사유": "원본 문서에 따르면 AGS 인력이 ServiceFLOW 계정을 발급받아 정형화된 지원 요청을 등록할 수 있으며, ServiceFLOW Main 화면에서 '문의접수'를 선택하는 것이 요청 절차의 시작이다. 따라서 '문의 접수' 선택이 가장 먼저 수행해야 하는 작업이 맞다.",
          "문제점": "특별히 발견된 문제점이나 개선사항은 없습니다."
        },
        "종합검증": "해당 문제는 충실도가 높으며, 문제의 해설이 원본 문서와 일치하고 이미지 기반 문제도 정확히 검증되었습니다."
      }
    },
    {
      "question_id": 2,
      "question_info": {
        "type": "OBJECTIVE",
        "difficulty_level": "NORMAL",
        "tags": [
          "이해력"
        ],
        "source_file": "basic_questions_20250703_215032.json",
        "document_name": "doc_2_ags_trouble_shooting_v1_1",
        "question": "ServiceFLOW에서 문의 접수 시, 한국어 구사자가 문의 티켓을 접수하는 것이 권고되는 이유는 무엇입니까?"
      },
      "quality_evaluation": {
        "적절성": {
          "점수": 5,
          "평가사유": "학습 목표는 ServiceFLOW에서의 문의 처리 과정을 이해하고, 한국어 구사자의 역할을 이해하는 것이며, 이 문제는 한국어 구사자의 역할과 중요성을 명확히 설명하고 있어 매우 적절함."
        },
        "난이도 적정성": {
          "점수": 4,
          "평가사유": "문제의 내용과 선택지는 쉽게 이해할 수 있지만, 조금 더 깊이 있는 이해를 요구하여 MEDIUM 레벨에 적합함."
        },
        "명확성 및 모호성 없음": {
          "점수": 5,
          "평가사유": "문제와 선택지가 명확하게 구분되어 있고, 해설도 명확하게 주어져 있어 모호성이 전혀 없음."
        },
        "정답 및 해설의 정확성": {
          "점수": 5,
          "평가사유": "해설에서 설명한 이유가 정확하게 문제의 의도를 반영하고 있으며, 정확한 의사 소통의 중요성을 명확히 설명하고 있음."
        },
        "학습적 가치 및 유용성": {
          "점수": 5,
          "평가사유": "이 문제를 풀면서 한국어 구사자의 역할과 정확한 의사 소통의 중요성을 이해할 수 있으며, 실무에서도 의사 소통의 중요성을 더욱 인지할 수 있어 높은 학습적 가치가 있음."
        },
        "Quality Score": 24,
        "Quality Score 최대": 25,
        "품질등급": "Excellent",
        "종합평가": "이 문제는 학습 목표에 매우 적절하게 부합하며, 난이도와 명확성 측면에서도 우수한 품질을 보여줍니다. 정확성과 학습적 가치 또한 뛰어나므로 즉시 사용이 가능하며, 추가적인 개선이 필요하지 않습니다."
      },
      "fidelity_evaluation": {
        "문서_충실도": {
          "점수": 2,
          "검증사유": "원본 문서에서 '한국어 구사자가 문의 티켓을 접수하는 것이 권고되는 이유'에 대한 구체적 내용이 '정확한 의사 소통을 통해 문제 해결 효율성을 높이기 위함'으로 설명되어 있습니다.",
          "문제점": ""
        },
        "종합검증": "해당 문제는 원본 문서 내용을 정확하게 반영하고 있으며, 충실도 점수 2점을 부여합니다."
      }
    },
    {
      "question_id": 3,
      "question_info": {
        "type": "OBJECTIVE",
        "difficulty_level": "NORMAL",
        "tags": [
          "이해력"
        ],
        "source_file": "basic_questions_20250703_215032.json",
        "document_name": "doc_2_ags_trouble_shooting_v1_1",
        "question": "ServiceFLOW에서 문의 접수 시, '문의 접수' 선택 후 다음으로 진행해야 할 단계는 무엇입니까?"
      },
      "quality_evaluation": {
        "적절성": {
          "점수": 4,
          "평가사유": "학습 목표인 'ServiceFLOW에서 문의 접수 시 다음 단계'에 적합한 문제이나, '서비스 모듈 선택'이라는 단계가 명확히 학습 목표와 부합하는지 조금 의문이 남음."
        },
        "난이도 적정성": {
          "점수": 4,
          "평가사유": "문제의 선택지가 명확하고 쉽게 이해되지만, '서비스 모듈 선택'이 다른 선택지와 비교했을 때 조금 더 어려울 수 있음."
        },
        "명확성 및 모호성 없음": {
          "점수": 4,
          "평가사유": "문제와 선택지가 명확하게 제시되어 있지만, '서비스 모듈 선택'이 다소 모호할 수 있음."
        },
        "정답 및 해설의 정확성": {
          "점수": 5,
          "평가사유": "해설이 정확하게 '서비스 모듈 선택'을 다음 단계로 설명하고 있으며, 논리적으로 이해하기 쉬움."
        },
        "학습적 가치 및 유용성": {
          "점수": 4,
          "평가사유": "이러한 상황에 대한 학습이 교육적 가치가 있으며, 실무에서도 유용하게 활용될 수 있음."
        },
        "Quality Score": 21,
        "Quality Score 최대": 25,
        "품질등급": "Good",
        "종합평가": "문제의 적절성과 난이도는 대체로 양호하나, '서비스 모듈 선택'이 명확히 목표와 부합하는지 재고해 보고, 선택지의 모호성을 개선하면 더 좋은 평가를 받을 수 있을 것임."
      },
      "fidelity_evaluation": {
        "문서_충실도": {
          "점수": 2,
          "검증사유": "원본 문서에서 'ServiceFlow Main 화면에서 '문의접수' 선택' 후 'ServiceFlow > 요청서 작성 > 시스템 서비스 계정 / > 협력직 ID 신청 (ServiceFlow) 선택하여기안' 단계가 설명되어 있습니다. 이에 따라 문의를 접수한 후에는 '서비스 모듈 선택' 단계가 진행되어야 합니다.",
          "문제점": ""
        },
        "종합검증": "주어진 문제에 대한 답변이 충분히 출처에 근거하고 있으며, 원본 문서와 일치하므로 문제에 대한 정확한 해답을 제공하고 있습니다."
      }
    },
    {
      "question_id": 4,
      "question_info": {
        "type": "OBJECTIVE",
        "difficulty_level": "NORMAL",
        "tags": [
          "이해력"
        ],
        "source_file": "basic_questions_20250703_215032.json",
        "document_name": "doc_2_ags_trouble_shooting_v1_1",
        "question": "다음 중 ServiceFLOW를 통해 문의 접수를 할 수 있는 사람은 누구입니까?"
      },
      "quality_evaluation": {
        "적절성": {
          "점수": 4,
          "평가사유": "학습 목표는 ServiceFLOW를 통한 문의 접수 가능한 대상을 알아보는 것이며, 이에 대한 적절한 문제로 평가됩니다. 다만, 보다 명확한 학습 목표 설정이 있었다면 더 높은 점수를 받을 수 있을 것입니다."
        },
        "난이도 적정성": {
          "점수": 4,
          "평가사유": "선택지가 명확하게 주어지고, 문제의 난이도도 중간 정도로 적절하게 설정되어 있습니다."
        },
        "명확성 및 모호성 없음": {
          "점수": 5,
          "평가사유": "문제와 선택지가 명확하게 구분되어 있고, 해설을 통해 추가적인 혼란을 줄일 수 있습니다."
        },
        "정답 및 해설의 정확성": {
          "점수": 5,
          "평가사유": "해설이 정확하게 AGS 인력이 ServiceFLOW를 통해 문의 접수 가능하다고 설명하고 있으며, 이는 명확하고 논리적입니다."
        },
        "학습적 가치 및 유용성": {
          "점수": 4,
          "평가사유": "이 문제를 풀면서 ServiceFLOW를 통한 문의 접수 대상에 대한 이해를 높일 수 있으며, 실무에서도 유용하게 활용할 수 있는 내용입니다."
        },
        "Quality Score": 22,
        "Quality Score 최대": 25,
        "품질등급": "Good",
        "종합평가": "문제의 적절성과 명확성은 높지만, 학습적 가치 측면에서 조금 더 발전할 여지가 있습니다. 추가적인 학습 자료나 예시를 통해 실무 적용 가능성을 강화할 수 있을 것입니다."
      },
      "fidelity_evaluation": {
        "문서_충실도": {
          "점수": 2,
          "검증사유": "원본 문서에서 'ServiceFLOW를 통해 문의 접수를 할 수 있는 사람은 AGS 인력'이라고 명시되어 있습니다. 이는 주어진 정답 'AGS 인력 (현장대리인 여부와 관계없이)'와 완전히 일치합니다.",
          "문제점": "특이사항 없음"
        },
        "종합검증": "주어진 문제는 원본 문서와 완벽하게 일치하여 충실도가 높습니다."
      }
    },
    {
      "question_id": 5,
      "question_info": {
        "type": "OBJECTIVE",
        "difficulty_level": "NORMAL",
        "tags": [
          "문제해결력"
        ],
        "source_file": "basic_questions_20250703_215032.json",
        "document_name": "doc_2_ags_trouble_shooting_v1_1",
        "question": "Tech VDI 환경에서 특정 프로그램 오류가 발생했을 때, ServiceFLOW를 통해 문의를 접수하려고 합니다. 가장 적절한 서비스 모듈 선택 방법은 무엇입니까?"
      },
      "quality_evaluation": {
        "적절성": {
          "점수": 5,
          "평가사유": "문제는 Tech VDI 환경에서 발생한 오류에 대한 서비스 모듈 선택 방법을 테스트하고자 함. 학습 목표와 수준에 매우 적절함."
        },
        "난이도 적정성": {
          "점수": 5,
          "평가사유": "문제는 단순한 선택지 중에서 가장 적합한 서비스 모듈을 선택하는 것으로 적절한 쉬운 수준임."
        },
        "명확성 및 모호성 없음": {
          "점수": 5,
          "평가사유": "문제와 선택지가 명확하게 제시되어 있고 모호함이 전혀 없음."
        },
        "정답 및 해설의 정확성": {
          "점수": 5,
          "평가사유": "정답인 'Tech VDI' 관련 서비스 모듈 선택이 명확하고 논리적으로 설명되어 있음."
        },
        "학습적 가치 및 유용성": {
          "점수": 4,
          "평가사유": "문제는 실무 상황을 시뮬레이션하여 적합한 서비스 모듈 선택 능력을 테스트하며 교육적 효과가 높음. 다만, 다양한 상황에 대한 선택지가 더 있으면 더 유용할 수 있음."
        },
        "Quality Score": 24,
        "Quality Score 최대": 25,
        "품질등급": "Excellent",
        "종합평가": "문제는 학습 목표에 매우 적절하고 적정한 난이도로 구성되어 있으며 명확성과 정확성이 뛰어나다. 다만, 선택지를 조금 더 다양하게 제시한다면 학습적 가치와 유용성을 높일 수 있을 것이다."
      },
      "fidelity_evaluation": {
        "문서_충실도": {
          "점수": 2,
          "검증사유": "원본 문서의 내용과 문제 해설이 일치합니다. 원본 문서에서 'Tech VDI' 환경에서 문제가 발생했을 때 ServiceFlow를 통해 문의를 접수하는 방법에 대한 설명이 충분히 제공되었습니다.",
          "문제점": "특정 프로그램 오류에 대한 구체적인 예시나 해결 방법 등 추가적인 정보가 있으면 더욱 도움이 될 수 있습니다."
        },
        "종합검증": "해당 문제는 원본 문서와 일치하여 충실도가 높습니다. 다만, 보다 구체적인 예시나 해결 방법을 추가로 제공하면 더욱 완벽한 교육적 효과를 기대할 수 있습니다."
      }
    },
    {
      "question_id": 6,
      "question_info": {
        "type": "SUBJECTIVE",
        "difficulty_level": "NORMAL",
        "tags": [
          "분석력"
        ],
        "source_file": "basic_questions_20250703_215032.json",
        "document_name": "doc_2_ags_trouble_shooting_v1_1",
        "question": "SK C&C의 AGS 인력이 ServiceFLOW를 사용하여 IT 지원을 요청하는 전체적인 프로세스를 설명하고, 각 단계에서 중요하게 고려해야 할 사항을 기술하시오."
      },
      "quality_evaluation": {
        "적절성": {
          "점수": 4,
          "평가사유": "문제는 SK C&C의 AGS 인력이 ServiceFLOW를 활용하여 IT 지원을 요청하는 프로세스를 설명하는 것으로, 학습 목표와 적합한 내용을 다루고 있습니다. 다만, 보다 구체적인 예시나 상황을 추가하면 더욱 적합할 것입니다."
        },
        "난이도 적정성": {
          "점수": 3,
          "평가사유": "문제의 난이도는 중간 정도로 적절하나, 좀 더 심화된 내용이나 응용력을 요구하는 부분이 더해진다면 레벨에 더 적합할 것입니다."
        },
        "명확성 및 모호성 없음": {
          "점수": 4,
          "평가사유": "문제와 예시 답안이 명확하게 제시되어 있어서 이해하기 쉽습니다. 다만, 각 단계에서 고려해야 할 사항을 더 구체적으로 설명한다면 더욱 명확해질 것입니다."
        },
        "정답 및 해설의 정확성": {
          "점수": 4,
          "평가사유": "예시 답안은 정확하고 논리적으로 설명되어 있습니다. 다만, 보다 다양한 해설이 추가된다면 더욱 다양한 시나리오에 대비할 수 있을 것입니다."
        },
        "학습적 가치 및 유용성": {
          "점수": 3,
          "평가사유": "문제는 교육적 효과가 있으나, 보다 실무적인 예시나 케이스 스터디를 추가한다면 더욱 유용할 것입니다."
        },
        "Quality Score": 18,
        "Quality Score 최대": 25,
        "품질등급": "Good",
        "종합평가": "해당 문제는 전반적으로 좋은 수준이나, 좀 더 구체적인 예시와 다양한 시나리오를 추가하여 실무적인 활용도를 높이고, 레벨에 맞는 난이도를 제시한다면 품질이 향상될 것입니다."
      },
      "fidelity_evaluation": {
        "문서_충실도": {
          "점수": 0,
          "검증사유": "원본 문서와 제시된 답안 간에는 일치하는 내용이 없습니다. 원본 문서에서는 AGS 인력이 ServiceFLOW 계정을 발급받아 업무 환경에 대한 정형화된 지원 요청을 직접 등록하는 내용이 주어졌지만, 답안에서는 ServiceFLOW를 통한 IT 지원 요청 프로세스와 중요 사항에 대한 설명이 제시되었습니다.",
          "문제점": "답안이 원본 문서의 내용과 일치하지 않고, 충실도가 낮습니다. 답안을 보완하여 원본 문서의 내용을 정확히 반영하도록 개선이 필요합니다."
        },
        "종합검증": "답안은 원본 문서의 내용과 일치하지 않아 충실도가 낮습니다. 보다 정확한 정보 제공을 통해 충실도를 향상시킬 필요가 있습니다."
      }
    },
    {
      "question_id": 7,
      "question_info": {
        "type": "SUBJECTIVE",
        "difficulty_level": "NORMAL",
        "tags": [
          "문제해결력"
        ],
        "source_file": "basic_questions_20250703_215032.json",
        "document_name": "doc_2_ags_trouble_shooting_v1_1",
        "question": "SK C&C M365 환경에서 메일 관련 문제 발생 시, AGS 인력이 ServiceFLOW를 통해 문의를 접수하는 상황을 가정하고, 문의 내용 작성 시 포함해야 할 필수 정보를 ..."
      },
      "quality_evaluation": {
        "적절성": {
          "점수": 4,
          "평가사유": "학습 목표인 SK C&C M365 환경에서 메일 관련 문제 발생 시 AGS 인력이 ServiceFLOW를 통해 문의를 접수하는 상황에 적합한 내용을 요구하고 있으며, 필수 정보 작성 방법을 학습 목표에 부합하게 제시하고 있습니다."
        },
        "난이도 적정성": {
          "점수": 3,
          "평가사유": "문의 내용 작성은 난이도가 MEDIUM 수준으로 적절하나, 좀 더 구체적인 예시나 해설을 통해 레벨에 맞는 안내가 더 필요할 수 있습니다."
        },
        "명확성 및 모호성 없음": {
          "점수": 5,
          "평가사유": "문의할 때 포함해야 할 필수 정보들을 명확하게 요구하고 있으며, 모호한 표현이나 해석이 없습니다."
        },
        "정답 및 해설의 정확성": {
          "점수": 4,
          "평가사유": "예시 답안에 포함된 필수 정보들이 정확하게 문제 상황을 파악하는 데 도움이 될 뿐만 아니라 논리적으로 구성되어 있습니다. 다만, 더 다양한 예시나 상황에 대한 해설이 추가되면 더욱 완벽할 것입니다."
        },
        "학습적 가치 및 유용성": {
          "점수": 4,
          "평가사유": "학습적 가치가 높은 문제로, 실무에서도 유용하게 활용될 수 있는 내용을 다루고 있습니다. 다만, 좀 더 다양한 상황에 대한 예시나 해설이 추가되면 더욱 유용할 것입니다."
        },
        "Quality Score": 20,
        "Quality Score 최대": 25,
        "품질등급": "Good",
        "종합평가": "문의 내용 작성에 대한 요구사항을 명확히 제시하고 있으며, 대부분의 측면에서 우수한 품질을 보여줍니다. 좀 더 다양한 예시와 해설을 추가하여 학습적 가치와 유용성을 향상시킬 수 있을 것입니다."
      },
      "fidelity_evaluation": {
        "문서_충실도": {
          "점수": 2,
          "검증사유": "원본 문서에서 SK C&C M365 환경에서 메일 관련 문제 발생 시 AGS 인력이 ServiceFLOW를 통해 문의를 접수하는 상황에 대한 필수 정보가 구체적으로 작성되어 있습니다. 문의 제목, 문제 발생 시점, 오류 메시지, 사용 환경, 문제 발생 빈도, 시도한 해결 방법 등이 명확히 포함되어 있습니다.",
          "문제점": "특이사항 없음"
        },
        "종합검증": "주어진 문제에 대한 답안은 원본 문서의 내용을 정확하게 반영하고 있으며, 필수 정보를 모두 포함하고 있어 문제 해결을 위한 충분한 가이드를 제공하고 있습니다."
      }
    },
    {
      "question_id": 8,
      "question_info": {
        "type": "OBJECTIVE",
        "difficulty_level": "NORMAL",
        "tags": [
          "이해력"
        ],
        "source_file": "basic_questions_20250703_215032.json",
        "document_name": "to_be_portal_process_fp_07_v1_0",
        "question": "SK C&C 차세대 ERP 재무 포털에서 탄소배출권 관련 정보를 확인할 수 있는 화면의 명칭으로 가장 적절한 것은 무엇입니까?"
      },
      "quality_evaluation": {
        "적절성": {
          "점수": 4,
          "평가사유": "문제가 SK C&C 차세대 ERP 재무 포털의 학습 목표와 수준에 적절하게 맞춰져 있습니다."
        },
        "난이도 적정성": {
          "점수": 4,
          "평가사유": "문제의 난이도가 중간 수준으로 적절하며, 'EASY/MEDIUM/HARD' 레벨에 적합합니다."
        },
        "명확성 및 모호성 없음": {
          "점수": 5,
          "평가사유": "문제와 선택지가 명확하게 제시되어 있고, 혼동을 줄 수 있는 모호성이 없습니다."
        },
        "정답 및 해설의 정확성": {
          "점수": 5,
          "평가사유": "정답 'FP-07.01 탄소배출권'이 명확히 제시되어 있으며, 해설 역시 정확하고 논리적입니다."
        },
        "학습적 가치 및 유용성": {
          "점수": 4,
          "평가사유": "이 문제를 풀면서 SK C&C 차세대 ERP 재무 포털에서의 탄소배출권 관련 정보에 대한 이해가 높아지며, 실무에 유용한 지식을 얻을 수 있습니다."
        },
        "Quality Score": 22,
        "Quality Score 최대": 25,
        "품질등급": "Excellent",
        "종합평가": "문제의 대부분의 측면이 우수하며, 학습 목표에 부합하고 유익한 내용을 담고 있습니다. 다만, 조금 더 다양한 유형의 문제를 추가하여 학습 효과를 높일 수 있을 것입니다."
      },
      "fidelity_evaluation": {
        "문서_충실도": {
          "점수": 2,
          "검증사유": "원본 문서에서 'FP-07.01 탄소배출권' 화면에서 탄소배출권 관련 정보를 확인할 수 있다는 내용이 명시되어 있습니다.",
          "문제점": ""
        },
        "종합검증": "해당 문제는 충실도가 높습니다. 원본 문서와 문제의 내용이 일치하며, 이미지 정보와 문제 내용도 일치합니다."
      }
    },
    {
      "question_id": 9,
      "question_info": {
        "type": "OBJECTIVE",
        "difficulty_level": "NORMAL",
        "tags": [
          "이해력"
        ],
        "source_file": "basic_questions_20250703_215032.json",
        "document_name": "to_be_portal_process_fp_07_v1_0",
        "question": "SK C&C 차세대 ERP 재무 포털의 탄소배출권 화면에서 확인할 수 있는 정보가 아닌 것은 무엇입니까?"
      },
      "quality_evaluation": {
        "적절성": {
          "점수": 5,
          "평가사유": "학습 목표는 SK C&C 차세대 ERP 재무 포털의 탄소배출권 화면에서 확인할 수 있는 정보를 파악하는 것이며, 이 문제는 해당 목표에 매우 적절하게 부합함"
        },
        "난이도 적정성": {
          "점수": 4,
          "평가사유": "문제의 난이도는 중간 정도로 적당히 설정되어 있으며, 선택지들 사이에 명확한 구분이 가능하므로 적정성을 가짐"
        },
        "명확성 및 모호성 없음": {
          "점수": 5,
          "평가사유": "문제와 선택지가 명확하게 제시되어 있고, 각 선택지의 내용 또한 모호함이 없이 명확하게 구분됨"
        },
        "정답 및 해설의 정확성": {
          "점수": 5,
          "평가사유": "해설에서 명시된 '탄소세 부과 내역'이 확인할 수 없는 정보임을 정확히 설명하고 있으며, 정확한 해설을 제공하고 있음"
        },
        "학습적 가치 및 유용성": {
          "점수": 4,
          "평가사유": "이 문제를 풀면서 학습자들은 탄소배출권 화면에서 어떤 정보를 확인할 수 있는지 명확히 이해할 수 있으며, 실무에서도 유용하게 활용할 수 있는 내용을 담고 있음"
        },
        "Quality Score": 23,
        "Quality Score 최대": 25,
        "품질등급": "Good",
        "종합평가": "해당 문제는 대부분의 기준에서 우수한 성적을 보여주고 있으며, 조금 더 다양한 유형의 문제를 추가하여 학습 효과를 높일 수 있을 것임"
      },
      "fidelity_evaluation": {
        "문서_충실도": {
          "점수": 2,
          "검증사유": "원본 문서에서 'SK C&C 차세대 ERP 재무 포털의 탄소배출권 화면'과 관련된 정보가 제공되지 않았으며, 탄소세 부과 내역에 대한 언급이 없습니다. 따라서, 주어진 선택지 중 '탄소세 부과 내역'은 확인할 수 있는 정보가 아니라고 판단됩니다.",
          "문제점": "특정 정보를 확인할 수 없다는 사실을 더 명확히 설명하는 부분이 추가되면 더욱 명확한 검증이 될 것입니다."
        },
        "종합검증": "주어진 문제는 원본 문서에 해당 정보가 없기 때문에 충실도가 높습니다. 다만, 추가적인 설명이 더해진다면 더욱 명확한 검증이 가능할 것입니다."
      }
    },
    {
      "question_id": 10,
      "question_info": {
        "type": "OBJECTIVE",
        "difficulty_level": "NORMAL",
        "tags": [
          "이해력"
        ],
        "source_file": "basic_questions_20250703_215032.json",
        "document_name": "to_be_portal_process_fp_07_v1_0",
        "question": "SK C&C 차세대 ERP 시스템에서 재무 포털을 통해 탄소배출권 관련 정보를 확인하는 것은 어떤 Activity(BTP)에 해당합니까?"
      },
      "quality_evaluation": {
        "적절성": {
          "점수": 5,
          "평가사유": "문제는 SK C&C 차세대 ERP 시스템의 재무 포털과 탄소배출권 관련 정보를 연결하여 학습 목표에 매우 적절하게 맞춰져 있습니다."
        },
        "난이도 적정성": {
          "점수": 5,
          "평가사유": "문제의 정답은 명확하고, 난이도가 적절히 설정되어 있어서 쉽게 파악할 수 있습니다."
        },
        "명확성 및 모호성 없음": {
          "점수": 5,
          "평가사유": "문제와 선택지가 명확하게 제시되어 있고, 혼동을 줄 수 있는 모호한 부분이 없습니다."
        },
        "정답 및 해설의 정확성": {
          "점수": 5,
          "평가사유": "해설이 정확하게 재무 포털과 탄소배출권 정보의 관련성을 설명하고 있으며, 정답 역시 정확하게 제시되어 있습니다."
        },
        "학습적 가치 및 유용성": {
          "점수": 5,
          "평가사유": "이 문제를 풀면서 SK C&C의 ERP 시스템과 재무 포털이 어떤 정보를 제공하는지에 대해 학습할 수 있으며, 실무에서도 유용한 지식을 얻을 수 있습니다."
        },
        "Quality Score": 25,
        "Quality Score 최대": 25,
        "품질등급": "Excellent",
        "종합평가": "해당 문제는 모든 평가 기준에서 우수한 성적을 보여주고 있습니다. 추가적인 개선이 필요하지 않습니다."
      },
      "fidelity_evaluation": {
        "문서_충실도": {
          "점수": 2,
          "검증사유": "원본 문서에서는 SK C&C PM 가이드에 등록된 협력사원으로 구매시스템, 협력직원 등록 후 익일 검색 가능하다고 언급하고 있습니다. 이와 같이 재무 포털을 통해 탄소배출권 관련 정보를 확인하는 것은 재무 Activity에 해당한다는 정보가 충분히 일치합니다.",
          "문제점": ""
        },
        "종합검증": "해당 문제는 충분한 근거를 바탕으로 정확히 답변되었으며, 원본 문서와도 일치하므로 문제의 충실도가 높습니다."
      }
    },
    {
      "question_id": 11,
      "question_info": {
        "type": "SUBJECTIVE",
        "difficulty_level": "NORMAL",
        "tags": [
          "분석력"
        ],
        "source_file": "basic_questions_20250703_215032.json",
        "document_name": "to_be_portal_process_fp_07_v1_0",
        "question": "SK C&C 차세대 ERP 재무 포털에서 탄소배출권 관련 정보를 확인하는 프로세스 체인을 간략하게 설명하고, 해당 정보가 기업의 의사 결정에 어떻게 활용될 수 있는지 구체적인 예를..."
      },
      "quality_evaluation": {
        "적절성": {
          "점수": 4,
          "평가사유": "문제가 SK C&C 차세대 ERP 재무 포털의 핵심 프로세스를 다루고 있어 학습 목표에 적절하며, 기업의 의사 결정과 관련된 내용으로 수준이 적당함."
        },
        "난이도 적정성": {
          "점수": 3,
          "평가사유": "문제의 난이도는 중간 수준으로, 탄소배출권 관련 정보를 이해하고 활용하는 과정을 설명하는 것은 중간 수준의 난이도에 적합함."
        },
        "명확성 및 모호성 없음": {
          "점수": 4,
          "평가사유": "문제와 예시 답안이 명확하게 구성되어 있으며, 탄소배출권 정보 확인 및 활용 과정이 명확하게 설명되어 있어 모호성이 거의 없음."
        },
        "정답 및 해설의 정확성": {
          "점수": 5,
          "평가사유": "예시 답안에서 제시된 프로세스 체인 및 기업의 의사 결정 예시가 정확하게 설명되어 있고, 논리적으로 이어져 있음."
        },
        "학습적 가치 및 유용성": {
          "점수": 4,
          "평가사유": "문제를 풀면서 기업이 탄소배출권 정보를 어떻게 활용할 수 있는지에 대한 교육적 가치가 높으며, 실무에서도 유용하게 활용될 수 있는 내용을 다루고 있음."
        },
        "Quality Score": 20,
        "Quality Score 최대": 25,
        "품질등급": "Good",
        "종합평가": "문제는 대체로 적절하고 명확하며, 정확한 내용을 다루고 있지만 난이도와 학습적 가치 측면에서 약간의 보완이 필요함. 난이도를 조금 더 다양하게 설정하고, 실무적 활용 예시를 더 다양하게 추가하는 것이 개선 방향이 될 수 있음."
      },
      "fidelity_evaluation": {
        "문서_충실도": {
          "점수": 2,
          "검증사유": "제시된 답안은 원본 문서의 'SK C&C 차세대 ERP 재무 포털에서 탄소배출권 관련 정보를 확인하는 프로세스 체인을 간략하게 설명하고, 해당 정보가 기업의 의사 결정에 어떻게 활용될 수 있는지' 요구사항을 정확히 충족합니다. 답안에서는 재무 포털을 통해 탄소배출권 정보를 확인하고, 이를 통해 기업이 탄소 배출 감축 목표 설정, 배출권 거래 전략 수립, 친환경 투자 결정 등에 활용할 수 있다는 구체적인 예시를 제시하고 있습니다.",
          "문제점": "특별히 발견된 문제점이 없습니다."
        },
        "종합검증": "주어진 문제에 대한 답안은 충분한 근거를 제시하고 있으며, 원본 문서의 내용을 정확하게 반영하고 있습니다. 따라서, 해당 답안은 높은 충실도를 가지고 있습니다."
      }
    },
    {
      "question_id": 12,
      "question_info": {
        "type": "SUBJECTIVE",
        "difficulty_level": "NORMAL",
        "tags": [
          "추론력"
        ],
        "source_file": "basic_questions_20250703_215032.json",
        "document_name": "to_be_portal_process_fp_07_v1_0",
        "question": "SK C&C가 차세대 ERP 시스템을 구축하면서 재무 포털에 탄소배출권 관련 기능을 추가한 이유는 무엇이라고 생각하십니까? 기업의 지속가능 경영 측면에서 그 중요성을 설명하시오."
      },
      "quality_evaluation": {
        "적절성": {
          "점수": 4,
          "평가사유": "문제가 기업의 지속가능 경영 측면에서 탄소배출권의 중요성을 파악하고자 하는 학습 목표에 적절하게 부합함."
        },
        "난이도 적정성": {
          "점수": 3,
          "평가사유": "문제의 난이도는 중간 수준으로 적당하나, 좀 더 구체적인 예시나 근거를 요구함으로써 조금 더 어려운 수준으로 조정할 필요가 있음."
        },
        "명확성 및 모호성 없음": {
          "점수": 4,
          "평가사유": "문제와 예시 답안이 명확하고 모호함이 거의 없으나, 좀 더 구체적인 사례나 설명이 추가될 경우 더 명확해질 수 있음."
        },
        "정답 및 해설의 정확성": {
          "점수": 5,
          "평가사유": "예시 답안이 정확하고 논리적으로 기업의 탄소배출권 관리의 중요성을 설명하고 있음."
        },
        "학습적 가치 및 유용성": {
          "점수": 4,
          "평가사유": "문제를 풀면서 기업의 지속가능 경영과 탄소배출권의 관련성을 이해하고 교육적 가치를 얻을 수 있음. 다만, 보다 다양한 관련 사례를 추가하면 더욱 유용할 것임."
        },
        "Quality Score": 20,
        "Quality Score 최대": 25,
        "품질등급": "Good",
        "종합평가": "문제는 기업의 지속가능 경영과 탄소배출권의 관련성을 이해하는 데 도움이 되지만, 좀 더 다양한 예시와 근거를 추가하여 학습적 가치를 향상시킬 필요가 있음."
      },
      "fidelity_evaluation": {
        "문서_충실도": {
          "점수": 2,
          "검증사유": "원본 문서에서는 SK C&C가 차세대 ERP 시스템을 구축하면서 재무 포털에 탄소배출권 관련 기능을 추가한 이유를 '기업의 지속가능 경영 측면에서 그 중요성을 설명하시오'라는 질문에 대한 답변으로 '탄소배출량 관리를 통해 환경 규제 준수 및 ESG 경영 강화. 지속가능 경영을 위한 핵심 지표 관리 및 투자 결정에 활용.'이 제시되어 있습니다. 이는 원본 문서의 내용과 완전히 일치하며, 출처에서 직접적으로 언급된 내용을 정확하게 반영하고 있습니다.",
          "문제점": ""
        },
        "종합검증": "주어진 문제에 대한 답변이 출처에 직접적으로 서술된 내용을 정확하게 반영하고 있으며, 원본 문서와의 일치도 높습니다. 따라서 이 문제에 대한 답변은 높은 충실도를 보여주고 있습니다."
      }
    }
  ]
}